.gitignore
MANIFEST.in
README.md
README.txt
collective.responsivetheme-configure.zcml
setup.cfg
setup.py
collective/__init__.py
collective.responsivetheme.egg-info/PKG-INFO
collective.responsivetheme.egg-info/SOURCES.txt
collective.responsivetheme.egg-info/dependency_links.txt
collective.responsivetheme.egg-info/entry_points.txt
collective.responsivetheme.egg-info/namespace_packages.txt
collective.responsivetheme.egg-info/not-zip-safe
collective.responsivetheme.egg-info/requires.txt
collective.responsivetheme.egg-info/top_level.txt
collective/responsivetheme/__init__.py
collective/responsivetheme/configure.zcml
collective/responsivetheme/profiles.zcml
collective/responsivetheme/setuphandlers.py
collective/responsivetheme/skins.zcml
collective/responsivetheme/tests.py
collective/responsivetheme/upgrades.py
collective/responsivetheme/version.txt
collective/responsivetheme/Extensions/Install.py
collective/responsivetheme/browser/__init__.py
collective/responsivetheme/browser/configure.zcml
collective/responsivetheme/browser/interfaces.py
collective/responsivetheme/browser/javascripts/ios-orientationchange-fix.js
collective/responsivetheme/browser/javascripts/plone-rwd-nav.js
collective/responsivetheme/browser/javascripts/respond.src.js
collective/responsivetheme/browser/javascripts/viewportchange.js
collective/responsivetheme/locales/README.txt
collective/responsivetheme/locales/collective.responsivetheme.pot
collective/responsivetheme/locales/es/LC_MESSAGES/.DS_Store
collective/responsivetheme/locales/es/LC_MESSAGES/collective.responsivetheme.mo
collective/responsivetheme/locales/es/LC_MESSAGES/collective.responsivetheme.po
collective/responsivetheme/locales/fr/.DS_Store
collective/responsivetheme/locales/fr/LC_MESSAGES/.DS_Store
collective/responsivetheme/locales/fr/LC_MESSAGES/collective.responsivetheme.po
collective/responsivetheme/locales/fr/LC_MESSAGES/plonetheme.diazo_responsivetheme.mo
collective/responsivetheme/locales/nl/LC_MESSAGES/collective.responsivetheme.mo
collective/responsivetheme/locales/nl/LC_MESSAGES/collective.responsivetheme.po
collective/responsivetheme/profiles/.DS_Store
collective/responsivetheme/profiles/default/browserlayer.xml
collective/responsivetheme/profiles/default/collective.responsivetheme_various.txt
collective/responsivetheme/profiles/default/cssregistry.xml
collective/responsivetheme/profiles/default/jsregistry.xml
