Metadata-Version: 1.0
Name: collective.responsivetheme
Version: 1.5.2
Summary: A responsive theme based on sunburst for Plone 4
Home-page: http://github.com/RobZoneNet/collective.responsivetheme
Author: Rob Porter
Author-email: robzonenet@gmail.com
License: GPL
Platform: UNKNOWN
Classifier: Framework :: Plone
Classifier: Programming Language :: Python
